musi/__init__.py
musi/main.py
musi-0.4.0.dist-info/METADATA
musi-0.4.0.dist-info/WHEEL
musi-0.4.0.dist-info/top_level.txt
musi-0.4.0.dist-info/RECORD
