Metadata-Version: 2.4
Name: musi
Version: 0.4.0
Summary: A music library based on the equal temperament
Author: piacode
Classifier: Programming Language :: Python :: 3
Classifier: License :: OSI Approved :: MIT License
Classifier: Operating System :: OS Independent
Requires-Python: >=3.7
Requires-Dist: numpy==1.26.4
Requires-Dist: pydub==0.25.1
